khatab/__init__.py
khatab/khatab.py
khatab_library-0.1.dist-info/METADATA
khatab_library-0.1.dist-info/WHEEL
khatab_library-0.1.dist-info/top_level.txt
khatab_library-0.1.dist-info/RECORD
